{
  "$schema": "./docs/project-state.schema.json",
  "version": 1,
  "updatedAt": "2026-07-13T15:45:00-04:00",
  "milestone": {
    "id": "SAFETY-OPS-001",
    "name": "Recommended private-alpha safety-operations foundation",
    "status": "active"
  },
  "git": {
    "branch": "agent/macos-session-requests-read",
    "latestCoherentCommit": "e01ba40",
    "workingTreeExpectedClean": true
  },
  "verification": {
    "status": "passed",
    "commands": [
      "xcodegen generate \u2014 success",
      "xcodebuild -scheme Litmo test \u2014 28/28 (Campfire+Trust+Profile+Requests)",
      "xcodebuild -scheme LitmoOps build unsigned \u2014 BUILD SUCCEEDED",
      "npm run state:check \u2014 pass",
      "Hosted macOS Native Build \u2014 pending on PR"
    ],
    "failures": []
  },
  "nextAction": "Review/merge MACOS-004 PR after hosted green. Also merge PR #81 vibe quiz when green. Ops stays locked.",
  "blockedBy": [
    "Legal/privacy/security review for destructive retention and deletion",
    "Qualified safeguarding/legal review for external escalation",
    "Named independent backup reviewer before external alpha and two-person permanent bans",
    "Apple signing credentials and reviewed staging configuration for a signed device/TestFlight build"
  ],
  "risks": [
    "macOS participant reads use developer env tokens; not production passkey sign-in.",
    "A listed session request is never consent.",
    "Litmo Ops remains non-operational until real staff authentication and authorization exist.",
    "ACCESS-001 still requires a physical founder VoiceOver smoke before it can be closed."
  ],
  "notes": [
    "PRs #72\u2013#80 are merged on main.",
    "MACOS-004 adds read-only session request lists (ADR 0048).",
    "PR #81 holds light vibe quiz expansion + flow polish."
  ]
}
